fluke/__init__.py
fluke/client.py
fluke/comm.py
fluke/config.py
fluke/evaluation.py
fluke/get.py
fluke/nets.py
fluke/run.py
fluke/server.py
fluke/algorithms/__init__.py
fluke/algorithms/apfl.py
fluke/algorithms/ccvr.py
fluke/algorithms/ditto.py
fluke/algorithms/dpfedavg.py
fluke/algorithms/fat.py
fluke/algorithms/fedala.py
fluke/algorithms/fedamp.py
fluke/algorithms/fedavg.py
fluke/algorithms/fedavgm.py
fluke/algorithms/fedaws.py
fluke/algorithms/fedbabu.py
fluke/algorithms/fedbn.py
fluke/algorithms/feddyn.py
fluke/algorithms/fedexp.py
fluke/algorithms/fedhp.py
fluke/algorithms/fedlc.py
fluke/algorithms/fedld.py
fluke/algorithms/fednh.py
fluke/algorithms/fednova.py
fluke/algorithms/fedopt.py
fluke/algorithms/fedper.py
fluke/algorithms/fedproto.py
fluke/algorithms/fedprox.py
fluke/algorithms/fedrep.py
fluke/algorithms/fedrod.py
fluke/algorithms/fedrs.py
fluke/algorithms/fedsam.py
fluke/algorithms/fedsgd.py
fluke/algorithms/gear.py
fluke/algorithms/kafe.py
fluke/algorithms/lg_fedavg.py
fluke/algorithms/moon.py
fluke/algorithms/per_fedavg.py
fluke/algorithms/pfedme.py
fluke/algorithms/scaffold.py
fluke/algorithms/superfed.py
fluke/data/__init__.py
fluke/data/datasets.py
fluke/data/support.py
fluke/distr/__init__.py
fluke/distr/client.py
fluke/distr/server.py
fluke/distr/utils.py
fluke/utils/__init__.py
fluke/utils/log.py
fluke/utils/model.py
fluke_fl-0.7.9.dist-info/licenses/LICENSE
fluke_fl-0.7.9.dist-info/METADATA
fluke_fl-0.7.9.dist-info/WHEEL
fluke_fl-0.7.9.dist-info/entry_points.txt
fluke_fl-0.7.9.dist-info/top_level.txt
fluke_fl-0.7.9.dist-info/RECORD
